starry_beta-0.3.0.data/data/starry_beta.maps/moon.jpg
starry_beta-0.3.0.data/data/starry_beta.maps/deathstar.jpg
starry_beta-0.3.0.data/data/starry_beta.maps/earth.jpg
starry_beta-0.3.0.data/data/starry_beta.maps/jupiter.jpg
starry_beta-0.3.0.dist-info/RECORD
starry_beta-0.3.0.dist-info/METADATA
starry_beta-0.3.0.dist-info/top_level.txt
starry_beta-0.3.0.dist-info/WHEEL
starry_beta-0.3.0.dist-info/LICENSE
starry_beta/_starry_mono_128.cpython-36m-x86_64-linux-gnu.so
starry_beta/_starry_spectral_128.cpython-36m-x86_64-linux-gnu.so
starry_beta/tables.py
starry_beta/_starry_spectral_64.cpython-36m-x86_64-linux-gnu.so
starry_beta/pybind_interface.cpp
starry_beta/__init__.py
starry_beta/kepler.py
starry_beta/_starry_mono_64.cpython-36m-x86_64-linux-gnu.so
starry_beta/maps/moon.jpg
starry_beta/maps/deathstar.jpg
starry_beta/maps/maps.py
starry_beta/maps/__init__.py
starry_beta/maps/plotting.py
starry_beta/maps/earth.jpg
starry_beta/maps/jupiter.jpg
