Metadata-Version: 2.1
Name: starry_beta
Version: 0.3.0
Summary: Analytic occultation light curves for astronomy.
Home-page: https://github.com/rodluger/starry_beta
Author: Rodrigo Luger
Author-email: rodluger@gmail.com
License: GPL
Platform: UNKNOWN
